PyGrabIt/Library.py
PyGrabIt/__init__.py
PyGrabIt/__main__.py
PyGrabIt-1.0.0.dist-info/METADATA
PyGrabIt-1.0.0.dist-info/WHEEL
PyGrabIt-1.0.0.dist-info/top_level.txt
PyGrabIt-1.0.0.dist-info/RECORD
