Metadata-Version: 2.1
Name: PyGrabIt
Version: 1.0.0
Summary: Python implementation of grabit toolbox.
Home-page: https://github.com/ludvikalkhoury/PyGrabIt.git
Author: Ludvik Alkhoury
Author-email: Ludvik.Alkhoury@gmail.com
